pycq/__init__.py
pycq/error.py
pycq/queue.py
pycq/version.py
pycq-0.4.2.dist-info/LICENSE
pycq-0.4.2.dist-info/METADATA
pycq-0.4.2.dist-info/WHEEL
pycq-0.4.2.dist-info/top_level.txt
pycq-0.4.2.dist-info/RECORD
