Metadata-Version: 2.1
Name: pycq
Version: 0.4.2
Summary: Simple distributed FIFO queue for Python using CockroachDB/PostgreSQL
Home-page: https://github.com/adrianchifor/pycq
Author: Adrian Chifor
Author-email: me@adrianchifor.com
License: Apache License 2.0
Keywords: cockroachdb postgresql distributed queue pubsub
Platform: UNKNOWN
Classifier: Development Status :: 4 - Beta
Classifier: Intended Audience :: Developers
Classifier: Intended Audience :: System Administrators
Classifier: Topic :: Software Development :: Libraries :: Python Modules
Classifier: Topic :: System :: Distributed Computing
Classifier: Topic :: System :: Systems Administration
Classifier: License :: OSI Approved :: Apache Software License
Classifier: Programming Language :: Python :: 3.6
Classifier: Programming Language :: Python :: 3.7
Requires-Python: >=3.6
Requires-Dist: psycopg2 (>=2.8.4)
